minishare/__init__.py
minishare/py310/__init__.pyc
minishare/py310/cache_utils.pyc
minishare/py310/cert_utils.pyc
minishare/py310/common_permission.pyc
minishare/py310/config.pyc
minishare/py310/device_id.pyc
minishare/py310/formula.pyc
minishare/py310/token_utils.pyc
minishare/py311/__init__.pyc
minishare/py311/cache_utils.pyc
minishare/py311/cert_utils.pyc
minishare/py311/common_permission.pyc
minishare/py311/config.pyc
minishare/py311/device_id.pyc
minishare/py311/formula.pyc
minishare/py311/token_utils.pyc
minishare/py312/__init__.pyc
minishare/py312/cache_utils.pyc
minishare/py312/cert_utils.pyc
minishare/py312/common_permission.pyc
minishare/py312/config.pyc
minishare/py312/device_id.pyc
minishare/py312/formula.pyc
minishare/py312/token_utils.pyc
minishare/py313/__init__.pyc
minishare/py313/cache_utils.pyc
minishare/py313/cert_utils.pyc
minishare/py313/common_permission.pyc
minishare/py313/config.pyc
minishare/py313/device_id.pyc
minishare/py313/formula.pyc
minishare/py313/token_utils.pyc
minishare/py314/__init__.pyc
minishare/py314/cache_utils.pyc
minishare/py314/cert_utils.pyc
minishare/py314/common_permission.pyc
minishare/py314/config.pyc
minishare/py314/device_id.pyc
minishare/py314/formula.pyc
minishare/py314/token_utils.pyc
minishare/py38/__init__.pyc
minishare/py38/cache_utils.pyc
minishare/py38/cert_utils.pyc
minishare/py38/common_permission.pyc
minishare/py38/config.pyc
minishare/py38/device_id.pyc
minishare/py38/formula.pyc
minishare/py38/token_utils.pyc
minishare/py39/__init__.pyc
minishare/py39/cache_utils.pyc
minishare/py39/cert_utils.pyc
minishare/py39/common_permission.pyc
minishare/py39/config.pyc
minishare/py39/device_id.pyc
minishare/py39/formula.pyc
minishare/py39/token_utils.pyc
minishare-0.1003.0.dist-info/METADATA
minishare-0.1003.0.dist-info/WHEEL
minishare-0.1003.0.dist-info/top_level.txt
minishare-0.1003.0.dist-info/RECORD
